gdstk/__init__.py
gdstk/_gdstk.cp311-win_amd64.pyd
gdstk/_gdstk.pyi
gdstk/py.typed
gdstk-0.9.56.dist-info/METADATA
gdstk-0.9.56.dist-info/WHEEL
gdstk-0.9.56.dist-info/licenses/LICENSE
gdstk-0.9.56.dist-info/RECORD
