Metadata-Version: 2.1
Name: gdstk
Version: 0.9.56
Summary: Python module for creation and manipulation of GDSII files.
Keywords: GDSII,OASIS,CAD,layout
Author-Email: "Lucas H. Gabrielli" <heitzmann@gmail.com>
License: Boost Software License - Version 1.0 - August 17th, 2003
Classifier: Development Status :: 3 - Alpha
Classifier: Environment :: Console
Classifier: Intended Audience :: Developers
Classifier: Intended Audience :: Manufacturing
Classifier: Intended Audience :: Science/Research
Classifier: License :: OSI Approved :: Boost Software License 1.0 (BSL-1.0)
Classifier: Operating System :: OS Independent
Classifier: Programming Language :: C++
Classifier: Programming Language :: Python
Classifier: Programming Language :: Python :: Implementation :: CPython
Classifier: Topic :: Scientific/Engineering :: Electronic Design Automation (EDA)
Classifier: Typing :: Typed
Project-URL: Documentation, https://heitzmann.github.io/gdstk/
Project-URL: Repository, https://github.com/heitzmann/gdstk
Project-URL: Changelog, https://github.com/heitzmann/gdstk/blob/main/CHANGELOG.md
Requires-Python: >=3.9
Requires-Dist: numpy
Requires-Dist: typing_extensions; python_version < "3.11"
Requires-Dist: sphinx; extra == "docs"
Requires-Dist: sphinx_rtd_theme; extra == "docs"
Requires-Dist: sphinx-inline-tabs; extra == "docs"
Requires-Dist: matplotlib; extra == "docs"
Provides-Extra: docs
